aqueduct/__init__.py
aqueduct/_version.py
aqueduct/api_client.py
aqueduct/aqueduct_client.py
aqueduct/artifact.py
aqueduct/check_artifact.py
aqueduct/dag.py
aqueduct/decorator.py
aqueduct/enums.py
aqueduct/error.py
aqueduct/flow.py
aqueduct/generic_artifact.py
aqueduct/github.py
aqueduct/logger.py
aqueduct/metric_artifact.py
aqueduct/operators.py
aqueduct/param_artifact.py
aqueduct/responses.py
aqueduct/schedule.py
aqueduct/table_artifact.py
aqueduct/templates.py
aqueduct/utils.py
aqueduct/constants/__init__.py
aqueduct/constants/exports.py
aqueduct/constants/metrics.py
aqueduct/integrations/__init__.py
aqueduct/integrations/google_sheets_integration.py
aqueduct/integrations/integration.py
aqueduct/integrations/s3_integration.py
aqueduct/integrations/salesforce_integration.py
aqueduct/integrations/sql_integration.py
aqueduct/tests/__init__.py
aqueduct/tests/dag_delta_test.py
aqueduct/tests/dag_test.py
aqueduct/tests/decorator_test.py
aqueduct/tests/decorators_with_without_parentheses_test.py
aqueduct/tests/metric_test.py
aqueduct/tests/serialization_test.py
aqueduct/tests/utils.py
aqueduct/tests/test_files/__init__.py
aqueduct/tests/test_files/python_function/__init__.py
aqueduct/tests/test_files/python_function/python_function.py
aqueduct/tests/test_files/python_function/test_dependency_folder/__init__.py
aqueduct/tests/test_files/python_function/test_dependency_folder/helper_function.py
cgwu_test_upload_1-0.0.1.dist-info/METADATA
cgwu_test_upload_1-0.0.1.dist-info/WHEEL
cgwu_test_upload_1-0.0.1.dist-info/top_level.txt
cgwu_test_upload_1-0.0.1.dist-info/RECORD
